dieyoung/__init__.py
dieyoung-0.0.7.dist-info/METADATA
dieyoung-0.0.7.dist-info/WHEEL
dieyoung-0.0.7.dist-info/entry_points.txt
dieyoung-0.0.7.dist-info/licenses/LICENSE
dieyoung-0.0.7.dist-info/RECORD
