Metadata-Version: 2.4
Name: dieyoung
Version: 0.0.7
Summary: Find (and kill) long running processes by name and arguments
Project-URL: Homepage, https://github.com/yaroslaff/dieyoung
Project-URL: Issues, https://github.com/yaroslaff/dieyoung/issues
Author-email: Yaroslav Polyakov <yaroslaff@gmail.com>
License-File: LICENSE
Keywords: filter,find,inspect,kill,long time,monitoring,old,process,ps,slow,smart
Classifier: License :: OSI Approved :: MIT License
Classifier: Operating System :: OS Independent
Classifier: Programming Language :: Python :: 3
Requires-Python: >=3.8
Requires-Dist: psutil>=6.0.0
Requires-Dist: rich-argparse>=1.5.2
Requires-Dist: rich>=13.7.1
